Royal_Mail_Rest_API-0.0.9.dist-info/DESCRIPTION.rst
Royal_Mail_Rest_API-0.0.9.dist-info/METADATA
Royal_Mail_Rest_API-0.0.9.dist-info/RECORD
Royal_Mail_Rest_API-0.0.9.dist-info/WHEEL
Royal_Mail_Rest_API-0.0.9.dist-info/entry_points.txt
Royal_Mail_Rest_API-0.0.9.dist-info/metadata.json
Royal_Mail_Rest_API-0.0.9.dist-info/top_level.txt
royal_mail_rest_api/__init__.py
royal_mail_rest_api/api.py
royal_mail_rest_api/errors.py
royal_mail_rest_api/example.py
royal_mail_rest_api/get_credentials.py
royal_mail_rest_api/shipping.py
royal_mail_rest_api/tools.py
royal_mail_rest_api/tracking.py
