Metadata-Version: 2.0
Name: Royal-Mail-Rest-API
Version: 0.0.9
Summary: A small helper for integrating python with Royal Mails Rest API
Home-page: https://github.com/bobspadger/royal_mail_rest_api
Author: Alex Hellier
Author-email: alex.hellier@gmail.com
License: MIT license
Download-URL: https://github.com/Bobspadger/royal_mail_rest_api
Project-URL: Source, https://github.com/bobspadger/royal_mail_rest_api
Project-URL: Documentation, http://royal-mail-rest-api.readthedocs.io/en/latest/index.html
Keywords: Royal Mail Rest API
Platform: UNKNOWN
Classifier: Development Status :: 2 - Pre-Alpha
Classifier: Intended Audience :: Developers
Classifier: License :: OSI Approved :: MIT License
Classifier: Natural Language :: English
Classifier: Programming Language :: Python :: 3.4
Classifier: Programming Language :: Python :: 3.5
Classifier: Programming Language :: Python :: 3.6
Requires-Dist: requests
